[
	{
		"__TYPE__": "SharedSliceContent",
		"variation": "default",
		"primary": {
			"heading": {
				"__TYPE__": "StructuredTextContent",
				"value": [
					{
						"type": "heading1",
						"content": {
							"text": "Bottom"
						}
					}
				]
			},
			"body": {
				"__TYPE__": "StructuredTextContent",
				"value": [
					{
						"type": "paragraph",
						"content": {
							"text": "Ea incididunt sunt et."
						}
					}
				]
			},
			"buy_button_text": {
				"__TYPE__": "FieldContent",
				"value": "either",
				"type": "Text"
			}
		},
		"items": []
	}
]